translator.v
`default_nettype none

module translator (
    input wire[7:0] in_ascii,
    output reg[19:0] out
);

    parameter bit[3:0] DASH = 4'b1110;
    parameter bit[1:0] DOT = 2'b10;

    always @ (in_ascii) begin
        casez (in_ascii)
            8'b00110000: out = { 5{DASH}};                          // ASCII 0
            8'b00110001: out = { {1{DOT}}, {4{DASH}}, {2'b0} };     // ASCII 1
            8'b00110010: out = { {2{DOT}}, {3{DASH}}, {4'b0} };     // ASCII 2
            8'b00110011: out = { {3{DOT}}, {2{DASH}}, {6'b0} };     // ASCII 3
            8'b00110100: out = { {4{DOT}}, {1{DASH}}, {8'b0} };     // ASCII 4
            8'b00110101: out = { {5{DOT}}, {0{DASH}}, {10'b0} };    // ASCII 5
            8'b00110110: out = { {1{DASH}}, {4{DOT}}, {8'b0} };     // ASCII 6
            8'b00110111: out = { {2{DASH}}, {3{DOT}}, {6'b0} };     // ASCII 7
            8'b00111000: out = { {3{DASH}}, {2{DOT}}, {4'b0} };     // ASCII 8
            8'b00111001: out = { {4{DASH}}, {1{DOT}}, {2'b0} };     // ASCII 9

            // ASCII A
            8'b01?00001: out = { DOT, DASH, 14'b0 };
            //ASCII B
            8'b01?00010: out = { DASH, {3{DOT}}, 10'b0 };
            //ASCII C
            8'b01?00011: out = { {2{DASH, DOT}}, 8'b0 };
            //ASCII D
            8'b01?00100: out = { DASH, {2{DOT}}, 12'b0};
            //ASCII E
            8'b01?00101: out = { DASH, 16'b0 };
            //ASCII F
            8'b01?00110: out = { {2{DOT}}, DASH, DOT, 10'b0 };
            //ASCII G
            8'b01?00111: out = { {2{DASH}}, DOT, 10'b0 };
            //ASCII H
            8'b01?01000: out = { {4{DOT}}, 12'b0 };
            //ASCII I
            8'b01?01001: out = { {2{DOT}}, 16'b0 };
            //ASCII J
            8'b01?01010: out = { DOT, {3{DASH}}, 6'b0 };
            //ASCII K
            8'b01?01011: out = { DASH, DOT, DASH, 10'b0 };
            //ASCII L
            8'b01?01100: out = { DOT, DASH, {2{DOT}}, 10'b0};
            //ASCII M
            8'b01?01101: out = { {2{DASH}}, 12'b0 };
            //ASCII N
            8'b01?01110: out = { DASH, DOT, 14'b0 };
            //ASCII O
            8'b01?01111: out = { {3{DASH}}, 8'b0 };
            //ASCII P
            8'b01?10000: out = { DOT, DASH, DASH, DOT, 8'b0 };
            //ASCII Q
            8'b01?10001: out = { {2{DASH}}, DOT, DASH, 6'b0};
            //ASCII R
            8'b01?10010: out = { DOT, DASH, DOT, 12'b0 };
            //ASCII S
            8'b01?10011: out = { DOT, DOT, DOT, 14'b0 };
            //ASCII T
            8'b01?10100: out = { DASH, 16'b0 };
            //ASCII U
            8'b01?10101: out = { DOT, DOT, DASH, 12'b0 };
            //ASCII V
            8'b01?10110: out = { {3{DOT}}, DASH, 10'b0 };
            //ASCII W
            8'b01?10111: out = { DOT, DASH, DASH, 10'b0 };
            //ASCII X
            8'b01?11000: out = { DASH, DOT, DOT, DASH, 8'b0 };
            //ASCII Y
            8'b01?11001: out = { DASH, DOT, {2{DASH}}, 6'b0 };
            //ASCII Z
            8'b01?11010: out = { {2{DASH}}, {2{DOT}}, 8'b0 };

            default : out = 0;
        endcase
    end
endmodule

translator-trace.vcd
$version Generated by VerilatedVcd $end
$timescale 1ps $end
 $scope module TOP $end
  $var wire 8 # in_ascii [7:0] $end
  $var wire 20 $ out [19:0] $end
  $scope module translator $end
   $var wire 8 # in_ascii [7:0] $end
   $var wire 20 $ out [19:0] $end
   $var wire 4 % DASH [3:0] $end
   $var wire 2 & DOT [1:0] $end
  $upscope $end
 $upscope $end
$enddefinitions $end


#48
b00110000 #
b11101110111011101110 $
b1110 %
b10 &
#49
b00110001 #
b10111011101110111000 $
#50
b00110010 #
b10101110111011100000 $
#51
b00110011 #
b10101011101110000000 $
#52
b00110100 #
b10101010111000000000 $
#53
b00110101 #
b10101010100000000000 $
#54
b00110110 #
b11101010101000000000 $
#55
b00110111 #
b11101110101010000000 $
#56
b00111000 #
b11101110111010100000 $
#57
b00111001 #
b11101110111011101000 $
#65
b01000001 #
b10111000000000000000 $
#66
b01000010 #
b11101010100000000000 $
#67
b01000011 #
b11101011101000000000 $
#68
b01000100 #
b11101010000000000000 $
#69
b01000101 #
b11100000000000000000 $
#70
b01000110 #
b10101110100000000000 $
#71
b01000111 #
b11101110100000000000 $
#72
b01001000 #
b10101010000000000000 $
#73
b01001001 #
b10100000000000000000 $
#74
b01001010 #
b10111011101110000000 $
#75
b01001011 #
b11101011100000000000 $
#76
b01001100 #
b10111010100000000000 $
#77
b01001101 #
b11101110000000000000 $
#78
b01001110 #
b11101000000000000000 $
#79
b01001111 #
b11101110111000000000 $
#80
b01010000 #
b10111011101000000000 $
#81
b01010001 #
b11101110101110000000 $
#82
b01010010 #
b10111010000000000000 $
#83
b01010011 #
b10101000000000000000 $
#84
b01010100 #
b11100000000000000000 $
#85
b01010101 #
b10101110000000000000 $
#86
b01010110 #
b10101011100000000000 $
#87
b01010111 #
b10111011100000000000 $
#88
b01011000 #
b11101010111000000000 $
#89
b01011001 #
b11101011101110000000 $
#90
b01011010 #
b11101110101000000000 $
#97
b01100001 #
b10111000000000000000 $
#98
b01100010 #
b11101010100000000000 $
#99
b01100011 #
b11101011101000000000 $
#100
b01100100 #
b11101010000000000000 $
#101
b01100101 #
b11100000000000000000 $
#102
b01100110 #
b10101110100000000000 $
#103
b01100111 #
b11101110100000000000 $
#104
b01101000 #
b10101010000000000000 $
#105
b01101001 #
b10100000000000000000 $
#106
b01101010 #
b10111011101110000000 $
#107
b01101011 #
b11101011100000000000 $
#108
b01101100 #
b10111010100000000000 $
#109
b01101101 #
b11101110000000000000 $
#110
b01101110 #
b11101000000000000000 $
#111
b01101111 #
b11101110111000000000 $
#112
b01110000 #
b10111011101000000000 $
#113
b01110001 #
b11101110101110000000 $
#114
b01110010 #
b10111010000000000000 $
#115
b01110011 #
b10101000000000000000 $
#116
b01110100 #
b11100000000000000000 $
#117
b01110101 #
b10101110000000000000 $
#118
b01110110 #
b10101011100000000000 $
#119
b01110111 #
b10111011100000000000 $
#120
b01111000 #
b11101010111000000000 $
#121
b01111001 #
b11101011101110000000 $
#122
b01111010 #
b11101110101000000000 $
